v6gzbmssdr/__init__.py
v6gzbmssdr/foo.py
v6gzbmssdr-0.0.1.dist-info/METADATA
v6gzbmssdr-0.0.1.dist-info/WHEEL
v6gzbmssdr-0.0.1.dist-info/RECORD
