Metadata-Version: 2.1
Name: v6gzbmssdr
Version: 0.0.1
Summary: 
Author: Vy Pho
Author-email: vy.pho@halliburton.com
Requires-Python: >=3.11,<4.0
Classifier: Programming Language :: Python :: 3
Classifier: Programming Language :: Python :: 3.11
Classifier: Programming Language :: Python :: 3.12
